LICENSE
bigearthnet_gdf_builder/__init__.py
bigearthnet_gdf_builder/builder.py
bigearthnet_gdf_builder-0.1.10.dist-info/entry_points.txt
bigearthnet_gdf_builder-0.1.10.dist-info/WHEEL
bigearthnet_gdf_builder-0.1.10.dist-info/METADATA
bigearthnet_gdf_builder-0.1.10.dist-info/license_files/LICENSE
bigearthnet_gdf_builder-0.1.10.dist-info/RECORD
