Metadata-Version: 2.1
Name: bigearthnet-gdf-builder
Version: 0.1.10
Summary: A package to generate and extend BigEarthNet GeoDataFrames.
License: Apache Software License 2.0
Author-email: Kai Norman Clasen <k.clasen@protonmail.com>
Requires-Python: >=3.8
Requires-Dist: appdirs>=1.4
Requires-Dist: bigearthnet-common>=2.4
Requires-Dist: fastcore>=1.3
Requires-Dist: geopandas>=0.11
Requires-Dist: natsort>=8
Requires-Dist: pyarrow>=6
Requires-Dist: pydantic>=1.8
Requires-Dist: pygeos>=0.12
Requires-Dist: typer[all]>=0.6
Project-URL: documentation, https://kai-tub.github.io/bigearthnet_gdf_builder
Project-URL: homepage, https://github.com/kai-tub/bigearthnet_gdf_builder/
Project-URL: repository, https://github.com/kai-tub/bigearthnet_gdf_builder/
